imWatermark.py
imWatermark-0.0.2.dist-info/LICENSE
imWatermark-0.0.2.dist-info/METADATA
imWatermark-0.0.2.dist-info/WHEEL
imWatermark-0.0.2.dist-info/top_level.txt
imWatermark-0.0.2.dist-info/RECORD
